distronode_compat/__init__.py
distronode_compat/_version.py
distronode_compat/config.py
distronode_compat/constants.py
distronode_compat/errors.py
distronode_compat/loaders.py
distronode_compat/ports.py
distronode_compat/prerun.py
distronode_compat/py.typed
distronode_compat/runtime.py
distronode_compat/schema.py
distronode_compat/types.py
distronode_compat-0.1.dev1.dist-info/LICENSE
distronode_compat-0.1.dev1.dist-info/METADATA
distronode_compat-0.1.dev1.dist-info/WHEEL
distronode_compat-0.1.dev1.dist-info/top_level.txt
distronode_compat-0.1.dev1.dist-info/RECORD
