Metadata-Version: 2.1
Name: distronode-compat
Version: 0.1.dev1
Summary: Distronode compatibility goodies
Author-email: Sorin Sbarnea <ssbarnea@redhat.com>
Maintainer-email: Sorin Sbarnea <ssbarnea@redhat.com>
License: MIT
Project-URL: homepage, https://github.com/distronode/distronode-compat
Project-URL: documentation, https://distronode-compat.readthedocs.io/
Project-URL: repository, https://github.com/distronode/distronode-compat
Project-URL: changelog, https://github.com/distronode/distronode-compat/releases
Keywords: distronode
Classifier: Development Status :: 5 - Production/Stable
Classifier: Environment :: Console
Classifier: Intended Audience :: Developers
Classifier: Intended Audience :: Information Technology
Classifier: Intended Audience :: System Administrators
Classifier: License :: OSI Approved :: MIT License
Classifier: Operating System :: OS Independent
Classifier: Programming Language :: Python :: 3
Classifier: Programming Language :: Python :: 3.9
Classifier: Programming Language :: Python :: 3.10
Classifier: Programming Language :: Python :: 3.11
Classifier: Programming Language :: Python :: 3.12
Classifier: Programming Language :: Python
Classifier: Topic :: System :: Systems Administration
Classifier: Topic :: Software Development :: Bug Tracking
Classifier: Topic :: Software Development :: Quality Assurance
Classifier: Topic :: Software Development :: Testing
Classifier: Topic :: Utilities
Requires-Python: >=3.9
License-File: LICENSE
Requires-Dist: distronode-core >=2.12
Requires-Dist: packaging
Requires-Dist: PyYAML
Requires-Dist: subprocess-tee >=0.4.1
Requires-Dist: jsonschema >=4.6.0
Requires-Dist: typing-extensions >=4.5.0 ; python_version < "3.10"
Provides-Extra: docs
Requires-Dist: argparse-manpage ; extra == 'docs'
Requires-Dist: black ; extra == 'docs'
Requires-Dist: mkdocs-ansible[lock] >=0.1.2 ; extra == 'docs'
Provides-Extra: test
Requires-Dist: coverage ; extra == 'test'
Requires-Dist: pip-tools ; extra == 'test'
Requires-Dist: pytest >=7.2.0 ; extra == 'test'
Requires-Dist: pytest-mock ; extra == 'test'
Requires-Dist: pytest-plus ; extra == 'test'
